{
"meta":{"test_sets":[],"test_metrics":[],"learn_metrics":[{"best_value":"Min","name":"RMSE"}],"launch_mode":"Train","parameters":"","iteration_count":100,"learn_sets":["learn"],"name":"experiment"},
"iterations":[
{"learn":[13.96962521],"iteration":0,"passed_time":0.1446175302,"remaining_time":14.31713549},
{"learn":[13.09082657],"iteration":1,"passed_time":0.1458483256,"remaining_time":7.146567954},
{"learn":[12.27861651],"iteration":2,"passed_time":0.146938058,"remaining_time":4.750997207},
{"learn":[11.53029884],"iteration":3,"passed_time":0.1478171785,"remaining_time":3.547612285},
{"learn":[10.87492512],"iteration":4,"passed_time":0.1487237942,"remaining_time":2.825752089},
{"learn":[10.38155225],"iteration":5,"passed_time":0.1495934358,"remaining_time":2.343630494},
{"learn":[9.857621344],"iteration":6,"passed_time":0.1504799712,"remaining_time":1.999233903},
{"learn":[9.411181059],"iteration":7,"passed_time":0.1513417972,"remaining_time":1.740430667},
{"learn":[8.998198398],"iteration":8,"passed_time":0.1522294849,"remaining_time":1.539209236},
{"learn":[8.588034504],"iteration":9,"passed_time":0.1531456597,"remaining_time":1.378310937},
{"learn":[8.232135915],"iteration":10,"passed_time":0.154050632,"remaining_time":1.246409659},
{"learn":[7.936645968],"iteration":11,"passed_time":0.1549399831,"remaining_time":1.136226543},
{"learn":[7.686327869],"iteration":12,"passed_time":0.1558353863,"remaining_time":1.042898355},
{"learn":[7.453139483],"iteration":13,"passed_time":0.1566120617,"remaining_time":0.962045522},
{"learn":[7.216574456],"iteration":14,"passed_time":0.1573243081,"remaining_time":0.8915044127},
{"learn":[7.018377399],"iteration":15,"passed_time":0.1579861035,"remaining_time":0.8294270432},
{"learn":[6.823313325],"iteration":16,"passed_time":0.1586153236,"remaining_time":0.7744159916},
{"learn":[6.666946823],"iteration":17,"passed_time":0.1592344535,"remaining_time":0.7254013993},
{"learn":[6.508910347],"iteration":18,"passed_time":0.1598625013,"remaining_time":0.6815190843},
{"learn":[6.386746007],"iteration":19,"passed_time":0.1604884649,"remaining_time":0.6419538594},
{"learn":[6.265973887],"iteration":20,"passed_time":0.1611154505,"remaining_time":0.6061009805},
{"learn":[6.169088554],"iteration":21,"passed_time":0.1617334181,"remaining_time":0.5734184823},
{"learn":[6.063254647],"iteration":22,"passed_time":0.162348059,"remaining_time":0.5435130671},
{"learn":[5.976012341],"iteration":23,"passed_time":0.1629593031,"remaining_time":0.5160377932},
{"learn":[5.901135024],"iteration":24,"passed_time":0.1635960383,"remaining_time":0.4907881148},
{"learn":[5.835939901],"iteration":25,"passed_time":0.1642412905,"remaining_time":0.4674559807},
{"learn":[5.775227205],"iteration":26,"passed_time":0.164904669,"remaining_time":0.4458533644},
{"learn":[5.723443194],"iteration":27,"passed_time":0.1655545806,"remaining_time":0.4257117786},
{"learn":[5.680032138],"iteration":28,"passed_time":0.166217919,"remaining_time":0.406947319},
{"learn":[5.627248312],"iteration":29,"passed_time":0.1669032816,"remaining_time":0.3894409903},
{"learn":[5.592690321],"iteration":30,"passed_time":0.1676397565,"remaining_time":0.3731336515},
{"learn":[5.544273978],"iteration":31,"passed_time":0.1683629147,"remaining_time":0.3577711938},
{"learn":[5.503344158],"iteration":32,"passed_time":0.1690283674,"remaining_time":0.3431788066},
{"learn":[5.478259921],"iteration":33,"passed_time":0.169770193,"remaining_time":0.3295539041},
{"learn":[5.442185155],"iteration":34,"passed_time":0.1704803953,"remaining_time":0.3166064485},
{"learn":[5.407844279],"iteration":35,"passed_time":0.1711752769,"remaining_time":0.3043116035},
{"learn":[5.383507306],"iteration":36,"passed_time":0.1718230943,"remaining_time":0.2925636471},
{"learn":[5.362378839],"iteration":37,"passed_time":0.1724891382,"remaining_time":0.2814296465},
{"learn":[5.340630083],"iteration":38,"passed_time":0.1731655829,"remaining_time":0.2708487322},
{"learn":[5.318674311],"iteration":39,"passed_time":0.1738256948,"remaining_time":0.2607385423},
{"learn":[5.302066897],"iteration":40,"passed_time":0.174450456,"remaining_time":0.2510384611},
{"learn":[5.284928558],"iteration":41,"passed_time":0.1751236843,"remaining_time":0.2418374688},
{"learn":[5.272330995],"iteration":42,"passed_time":0.1757970428,"remaining_time":0.2330332893},
{"learn":[5.261014227],"iteration":43,"passed_time":0.1762351001,"remaining_time":0.2242992183},
{"learn":[5.229469639],"iteration":44,"passed_time":0.1769429978,"remaining_time":0.2162636639},
{"learn":[5.215020572],"iteration":45,"passed_time":0.1776029695,"remaining_time":0.2084904424},
{"learn":[5.193062414],"iteration":46,"passed_time":0.1782732819,"remaining_time":0.2010315732},
{"learn":[5.180484848],"iteration":47,"passed_time":0.1789373818,"remaining_time":0.1938488303},
{"learn":[5.165159502],"iteration":48,"passed_time":0.1795953696,"remaining_time":0.1869257928},
{"learn":[5.141982763],"iteration":49,"passed_time":0.1802637782,"remaining_time":0.1802637782},
{"learn":[5.131085119],"iteration":50,"passed_time":0.1809479884,"remaining_time":0.1738519889},
{"learn":[5.115896901],"iteration":51,"passed_time":0.181675836,"remaining_time":0.1677007717},
{"learn":[5.102227813],"iteration":52,"passed_time":0.1823387536,"remaining_time":0.1616966306},
{"learn":[5.092694221],"iteration":53,"passed_time":0.183019527,"remaining_time":0.155905523},
{"learn":[5.084135611],"iteration":54,"passed_time":0.1837326351,"remaining_time":0.1503267015},
{"learn":[5.067392027],"iteration":55,"passed_time":0.1844202422,"remaining_time":0.1449016188},
{"learn":[5.05548496],"iteration":56,"passed_time":0.1851201839,"remaining_time":0.1396520686},
{"learn":[5.037754059],"iteration":57,"passed_time":0.1857520994,"remaining_time":0.134510141},
{"learn":[5.018441657],"iteration":58,"passed_time":0.1864111493,"remaining_time":0.1295399512},
{"learn":[5.009952596],"iteration":59,"passed_time":0.1871127243,"remaining_time":0.1247418162},
{"learn":[5.000684433],"iteration":60,"passed_time":0.1877738683,"remaining_time":0.1200521453},
{"learn":[4.982819001],"iteration":61,"passed_time":0.1884235394,"remaining_time":0.1154853951},
{"learn":[4.966552282],"iteration":62,"passed_time":0.1890791824,"remaining_time":0.111046504},
{"learn":[4.948387795],"iteration":63,"passed_time":0.189759535,"remaining_time":0.1067397384},
{"learn":[4.933079332],"iteration":64,"passed_time":0.1904729537,"remaining_time":0.1025623597},
{"learn":[4.923067166],"iteration":65,"passed_time":0.1911485868,"remaining_time":0.09847048409},
{"learn":[4.91587203],"iteration":66,"passed_time":0.1918015444,"remaining_time":0.0944694174},
{"learn":[4.906625327],"iteration":67,"passed_time":0.1924196322,"remaining_time":0.09055041517},
{"learn":[4.895848666],"iteration":68,"passed_time":0.1930330607,"remaining_time":0.0867249983},
{"learn":[4.886562569],"iteration":69,"passed_time":0.1936733931,"remaining_time":0.08300288276},
{"learn":[4.876525557],"iteration":70,"passed_time":0.1943036653,"remaining_time":0.07936346894},
{"learn":[4.866771122],"iteration":71,"passed_time":0.1949697793,"remaining_time":0.07582158085},
{"learn":[4.860489381],"iteration":72,"passed_time":0.1956283282,"remaining_time":0.07235568303},
{"learn":[4.846895943],"iteration":73,"passed_time":0.1963972681,"remaining_time":0.06900444555},
{"learn":[4.830532583],"iteration":74,"passed_time":0.1970859874,"remaining_time":0.06569532913},
{"learn":[4.818616331],"iteration":75,"passed_time":0.1977975825,"remaining_time":0.06246239446},
{"learn":[4.806132466],"iteration":76,"passed_time":0.1984846985,"remaining_time":0.05928763722},
{"learn":[4.800479202],"iteration":77,"passed_time":0.1991403015,"remaining_time":0.05616777734},
{"learn":[4.797819002],"iteration":78,"passed_time":0.1995835592,"remaining_time":0.0530538575},
{"learn":[4.786614428],"iteration":79,"passed_time":0.2002500539,"remaining_time":0.05006251349},
{"learn":[4.777804595],"iteration":80,"passed_time":0.2009029415,"remaining_time":0.04712538133},
{"learn":[4.767203373],"iteration":81,"passed_time":0.2015721617,"remaining_time":0.04424754769},
{"learn":[4.752577047],"iteration":82,"passed_time":0.2022368929,"remaining_time":0.04142201421},
{"learn":[4.743678884],"iteration":83,"passed_time":0.2028881672,"remaining_time":0.03864536518},
{"learn":[4.737404981],"iteration":84,"passed_time":0.2035764155,"remaining_time":0.0359252498},
{"learn":[4.728022428],"iteration":85,"passed_time":0.2042082809,"remaining_time":0.03324320852},
{"learn":[4.723347156],"iteration":86,"passed_time":0.2048515091,"remaining_time":0.03060999561},
{"learn":[4.717517757],"iteration":87,"passed_time":0.2055138856,"remaining_time":0.02802462077},
{"learn":[4.709503034],"iteration":88,"passed_time":0.2061369634,"remaining_time":0.02547760222},
{"learn":[4.703039995],"iteration":89,"passed_time":0.2068084382,"remaining_time":0.02297871535},
{"learn":[4.696059284],"iteration":90,"passed_time":0.2074641413,"remaining_time":0.02051843156},
{"learn":[4.686066202],"iteration":91,"passed_time":0.2081312874,"remaining_time":0.01809837282},
{"learn":[4.674543063],"iteration":92,"passed_time":0.2088229526,"remaining_time":0.01571785665},
{"learn":[4.671858724],"iteration":93,"passed_time":0.2094402789,"remaining_time":0.01336852844},
{"learn":[4.6586434],"iteration":94,"passed_time":0.2101444992,"remaining_time":0.0110602368},
{"learn":[4.650850795],"iteration":95,"passed_time":0.2107684688,"remaining_time":0.008782019533},
{"learn":[4.647951816],"iteration":96,"passed_time":0.2113870276,"remaining_time":0.00653774312},
{"learn":[4.636294688],"iteration":97,"passed_time":0.212049374,"remaining_time":0.004327538245},
{"learn":[4.629521481],"iteration":98,"passed_time":0.2126951673,"remaining_time":0.002148436033},
{"learn":[4.625948565],"iteration":99,"passed_time":0.2133573334,"remaining_time":0}
]}